{
    "intents": [
        { "tag": "greeting", "patterns": ["Hello", "Hi", "How are you?", "How's it going?", "Nice to meet you"], "responses": ["Hey", "Hi", "Hello"], "context_set": "" },
        { "tag": "goodbye", "patterns": ["Bye", "See you later", "Goodbye"], "responses": ["See you later", "Have a nice day", "Bye! Come back again soon"] },
        { "tag": "thanks", "patterns": ["Thanks", "Thank you", "That's helpful"], "responses": ["Happy to help!", "Any time!", "My pleasure"] }
    ]
}
